genson/__init__.py
genson/__main__.py
genson_wheel-1.3.0.dist-info/AUTHORS.rst
genson_wheel-1.3.0.dist-info/LICENSE
genson_wheel-1.3.0.dist-info/METADATA
genson_wheel-1.3.0.dist-info/WHEEL
genson_wheel-1.3.0.dist-info/entry_points.txt
genson_wheel-1.3.0.dist-info/top_level.txt
genson_wheel-1.3.0.dist-info/zip-safe
genson_wheel-1.3.0.dist-info/RECORD
