Metadata-Version: 2.1
Name: genson-wheel
Version: 1.3.0
Summary: GenSON is a powerful, user-friendly JSON Schema generator.
Home-page: https://github.com/wolverdude/genson/
Download-URL: https://github.com/wolverdude/GenSON/tarball/v0.2s.0
Author: Jon Wolverton
Author-email: wolverton.jr@gmail.com
License: MIT
Keywords: json, schema, json-schema, jsonschema, object, generate,generator, builder, merge, draft 7, validate, validation
Classifier: Development Status :: 5 - Production/Stable
Classifier: Environment :: Console
Classifier: Intended Audience :: Developers
Classifier: Natural Language :: English
Classifier: License :: OSI Approved :: MIT License
Classifier: Operating System :: OS Independent
Classifier: Programming Language :: Python
Classifier: Programming Language :: Python :: 3
Classifier: Programming Language :: Python :: 3.7
Classifier: Programming Language :: Python :: 3.8
Classifier: Programming Language :: Python :: 3.9
Classifier: Programming Language :: Python :: 3.10
Classifier: Programming Language :: Python :: 3.11
Classifier: Topic :: Software Development :: Code Generators
Classifier: Topic :: Software Development :: Libraries :: Python Modules
Classifier: Topic :: Utilities
License-File: LICENSE
License-File: AUTHORS.rst
